<?xml version="1.0" encoding="utf-8" standalone="yes"?>
<imgdir name="blueCave2.img">
  <imgdir name="bsc">
    <canvas name="0">
      <vector name="origin" x="0" y="0" />
    </canvas>
    <canvas name="1">
      <vector name="origin" x="0" y="0" />
    </canvas>
    <canvas name="2">
      <vector name="origin" x="0" y="0" />
    </canvas>
  </imgdir>
  <imgdir name="edD">
    <canvas name="0">
      <vector name="origin" x="20" y="0" />
      <int name="z" value="-5" />
    </canvas>
  </imgdir>
  <imgdir name="edU">
    <canvas name="0">
      <imgdir name="foothold">
        <vector name="0" x="-27" y="0" />
        <vector name="1" x="-27" y="-20" />
        <vector name="2" x="27" y="-20" />
        <vector name="3" x="27" y="0" />
      </imgdir>
      <vector name="origin" x="20" y="22" />
      <int name="z" value="-5" />
    </canvas>
  </imgdir>
  <imgdir name="enH0">
    <canvas name="0">
      <imgdir name="foothold">
        <vector name="0" x="-1" y="-20" />
        <vector name="1" x="91" y="-20" />
      </imgdir>
      <vector name="origin" x="0" y="24" />
      <int name="z" value="-4" />
    </canvas>
    <canvas name="1">
      <imgdir name="foothold">
        <vector name="0" x="-1" y="-20" />
        <vector name="1" x="91" y="-20" />
      </imgdir>
      <vector name="origin" x="0" y="23" />
      <int name="z" value="-4" />
    </canvas>
  </imgdir>
  <imgdir name="enH1">
    <canvas name="0">
      <vector name="origin" x="0" y="0" />
      <int name="z" value="-4" />
    </canvas>
    <canvas name="1">
      <vector name="origin" x="0" y="0" />
      <int name="z" value="-4" />
    </canvas>
  </imgdir>
  <imgdir name="enV0">
    <canvas name="0">
      <imgdir name="foothold">
        <vector name="0" x="-27" y="68" />
        <vector name="1" x="-27" y="0" />
      </imgdir>
      <vector name="origin" x="22" y="0" />
      <int name="z" value="-3" />
    </canvas>
    <canvas name="1">
      <imgdir name="foothold">
        <vector name="0" x="-27" y="68" />
        <vector name="1" x="-27" y="0" />
      </imgdir>
      <vector name="origin" x="20" y="0" />
      <int name="z" value="-3" />
    </canvas>
  </imgdir>
  <imgdir name="enV1">
    <canvas name="0">
      <imgdir name="foothold">
        <vector name="0" x="27" y="0" />
        <vector name="1" x="27" y="68" />
      </imgdir>
      <vector name="origin" x="0" y="0" />
      <int name="z" value="-3" />
    </canvas>
    <canvas name="1">
      <imgdir name="foothold">
        <vector name="0" x="27" y="0" />
        <vector name="1" x="27" y="68" />
      </imgdir>
      <vector name="origin" x="0" y="0" />
      <int name="z" value="-3" />
    </canvas>
  </imgdir>
  <imgdir name="info" />
  <imgdir name="slLD">
    <canvas name="0">
      <vector name="origin" x="90" y="0" />
      <int name="z" value="-2" />
    </canvas>
  </imgdir>
  <imgdir name="slLU">
    <canvas name="0">
      <imgdir name="foothold">
        <vector name="0" x="-90" y="-20" />
        <vector name="1" x="-90" y="-37" />
        <vector name="2" x="-64" y="-37" />
        <vector name="3" x="-64" y="-59" />
        <vector name="4" x="-33" y="-59" />
        <vector name="5" x="-29" y="-80" />
        <vector name="6" x="0" y="-80" />
      </imgdir>
      <vector name="origin" x="90" y="82" />
      <int name="z" value="-2" />
    </canvas>
    <canvas name="1">
      <imgdir name="foothold">
        <vector name="0" x="-90" y="-20" />
        <vector name="1" x="0" y="-80" />
      </imgdir>
      <vector name="origin" x="90" y="82" />
      <int name="z" value="-2" />
    </canvas>
  </imgdir>
  <imgdir name="slRD">
    <canvas name="0">
      <vector name="origin" x="0" y="0" />
      <int name="z" value="-2" />
    </canvas>
  </imgdir>
  <imgdir name="slRU">
    <canvas name="0">
      <imgdir name="foothold">
        <vector name="0" x="0" y="-80" />
        <vector name="1" x="29" y="-80" />
        <vector name="2" x="30" y="-63" />
        <vector name="3" x="57" y="-63" />
        <vector name="4" x="57" y="-39" />
        <vector name="5" x="90" y="-39" />
        <vector name="6" x="90" y="-20" />
      </imgdir>
      <vector name="origin" x="0" y="83" />
      <int name="z" value="-2" />
    </canvas>
    <canvas name="1">
      <imgdir name="foothold">
        <vector name="0" x="0" y="-80" />
        <vector name="1" x="90" y="-20" />
      </imgdir>
      <vector name="origin" x="0" y="82" />
      <int name="z" value="-2" />
    </canvas>
  </imgdir>
</imgdir>